rc/__init__.py
rc/utils/DictUtils.py
rc/utils/__init__.py
rcpyutils/DictUtils.py
rcpyutils/__init__.py
rcpyutils-1.0.5.data/data/Pipfile
rcpyutils-1.0.5.dist-info/LICENSE
rcpyutils-1.0.5.dist-info/METADATA
rcpyutils-1.0.5.dist-info/WHEEL
rcpyutils-1.0.5.dist-info/top_level.txt
rcpyutils-1.0.5.dist-info/RECORD
