Metadata-Version: 2.1
Name: rcpyutils
Version: 1.0.5
Summary: A personal collection of Python tools for development
Home-page: https://github.com/St4rG00se/rcpyutils
Author: St4rG00se
Author-email: rollandcyrille@free.fr
License: MIT
Platform: UNKNOWN
License-File: LICENSE
